newportxps/XPS_C8_drivers.py
newportxps/__init__.py
newportxps/debugtime.py
newportxps/debugtimer.py
newportxps/ftp_wrapper.py
newportxps/newportxps.py
newportxps/utils.py
newportxps/version.py
newportxps-2025.1.0.dist-info/licenses/LICENSE
newportxps-2025.1.0.dist-info/METADATA
newportxps-2025.1.0.dist-info/WHEEL
newportxps-2025.1.0.dist-info/top_level.txt
newportxps-2025.1.0.dist-info/RECORD
